datashow/__init__.py
datashow/admin.py
datashow/apps.py
datashow/db.py
datashow/fields.py
datashow/formatters.py
datashow/forms.py
datashow/models.py
datashow/query.py
datashow/settings.py
datashow/table.py
datashow/urls.py
datashow/views.py
datashow/locale/de/LC_MESSAGES/django.po
datashow/migrations/0001_initial.py
datashow/migrations/0002_column_facet_count.py
datashow/migrations/0003_table_row_description_template_and_more.py
datashow/migrations/__init__.py
datashow/static/datashow/css/datashow.css
datashow/static/datashow/js/htmx.min.js
datashow/templates/datashow/_filterform.html
datashow/templates/datashow/_table.html
datashow/templates/datashow/base.html
datashow/templates/datashow/dataset_index.html
datashow/templates/datashow/dataset_row.html
datashow/templates/datashow/dataset_sql.html
datashow/templates/datashow/dataset_table.html
datashow/templates/datashow/pagination.html
datashow/templates/datashow/widgets/range.html
datashow/templatetags/__init__.py
datashow/templatetags/datashow_tags.py
django_datashow-0.1.10.dist-info/METADATA
django_datashow-0.1.10.dist-info/WHEEL
django_datashow-0.1.10.dist-info/licenses/LICENSE
django_datashow-0.1.10.dist-info/RECORD
