Metadata-Version: 2.4
Name: django-datashow
Version: 0.1.10
Summary: Present your datasets on your django site
License-File: LICENSE
Requires-Python: >=3.10
Requires-Dist: django-admin-sortable2>=2
Requires-Dist: django>=4.2
Requires-Dist: markdown>=3.7
